{
  "version": 1,
  "updated_at": "2026-07-15T18:44:13.789250Z",
  "approved_cards": 49,
  "pending_candidates": 319,
  "last_run": {
    "github_run_id": "29441570970",
    "source": "workflow_run",
    "started_at": "2026-07-15T18:41:41.647004Z",
    "finished_at": "2026-07-15T18:44:13.789024Z",
    "duration_seconds": 152.14,
    "target_new_cards": 5,
    "rounds": 1,
    "pool_before": 343,
    "pool_after": 319,
    "processed": 24,
    "proposals": 16,
    "reviewed": 16,
    "added": 5,
    "pass_rate": 20.8,
    "input_tokens": 16482,
    "output_tokens": 8145,
    "filters": {
      "before_ai": {
        "invalid_record": 0,
        "duplicate_source": 0,
        "seen_recently": 0,
        "low_information": 0,
        "explicit_topic_selected": 24,
        "random_selected": 0,
        "average_hook_score": 7
      },
      "before_review": {
        "low_confidence": 0,
        "missing_candidate": 0,
        "bad_title": 0,
        "bad_category": 0,
        "similar_title": 0,
        "semantic_duplicate": 0
      },
      "final": {
        "model_rejected": 0,
        "score_below_78": 0,
        "bad_title": 0,
        "bad_category": 0,
        "evidence_mismatch": 1,
        "duplicate_source": 0,
        "similar_title": 0,
        "semantic_duplicate": 0
      }
    },
    "source_stats": {
      "维基主题分类": {
        "processed": 23,
        "accepted": 4
      },
      "NASA APOD": {
        "processed": 1,
        "accepted": 1
      }
    },
    "quality": {
      "category_distribution": {
        "科学": 16,
        "科技": 9,
        "生物": 8,
        "历史": 7,
        "生活": 5,
        "艺术": 3,
        "综合": 1
      },
      "new_category_distribution": {
        "生物": 2,
        "科技": 2,
        "科学": 1
      },
      "source_pass_rates": {
        "维基主题分类": {
          "processed": 23,
          "accepted": 4,
          "pass_rate": 17.4
        },
        "NASA APOD": {
          "processed": 1,
          "accepted": 1,
          "pass_rate": 100.0
        }
      },
      "review_pass_rate": 31.2,
      "processed_pass_rate": 20.8,
      "evidence_mismatch": 1,
      "evidence_mismatch_rate": 6.2
    }
  },
  "recent_runs": [
    {
      "github_run_id": "29441570970",
      "source": "workflow_run",
      "started_at": "2026-07-15T18:41:41.647004Z",
      "finished_at": "2026-07-15T18:44:13.789024Z",
      "duration_seconds": 152.14,
      "target_new_cards": 5,
      "rounds": 1,
      "pool_before": 343,
      "pool_after": 319,
      "processed": 24,
      "proposals": 16,
      "reviewed": 16,
      "added": 5,
      "pass_rate": 20.8,
      "input_tokens": 16482,
      "output_tokens": 8145,
      "filters": {
        "before_ai": {
          "invalid_record": 0,
          "duplicate_source": 0,
          "seen_recently": 0,
          "low_information": 0,
          "explicit_topic_selected": 24,
          "random_selected": 0,
          "average_hook_score": 7
        },
        "before_review": {
          "low_confidence": 0,
          "missing_candidate": 0,
          "bad_title": 0,
          "bad_category": 0,
          "similar_title": 0,
          "semantic_duplicate": 0
        },
        "final": {
          "model_rejected": 0,
          "score_below_78": 0,
          "bad_title": 0,
          "bad_category": 0,
          "evidence_mismatch": 1,
          "duplicate_source": 0,
          "similar_title": 0,
          "semantic_duplicate": 0
        }
      },
      "source_stats": {
        "维基主题分类": {
          "processed": 23,
          "accepted": 4
        },
        "NASA APOD": {
          "processed": 1,
          "accepted": 1
        }
      },
      "quality": {
        "category_distribution": {
          "科学": 16,
          "科技": 9,
          "生物": 8,
          "历史": 7,
          "生活": 5,
          "艺术": 3,
          "综合": 1
        },
        "new_category_distribution": {
          "生物": 2,
          "科技": 2,
          "科学": 1
        },
        "source_pass_rates": {
          "维基主题分类": {
            "processed": 23,
            "accepted": 4,
            "pass_rate": 17.4
          },
          "NASA APOD": {
            "processed": 1,
            "accepted": 1,
            "pass_rate": 100.0
          }
        },
        "review_pass_rate": 31.2,
        "processed_pass_rate": 20.8,
        "evidence_mismatch": 1,
        "evidence_mismatch_rate": 6.2
      }
    },
    {
      "github_run_id": "29367135639",
      "source": "workflow_run",
      "started_at": "2026-07-14T20:48:35.108087Z",
      "finished_at": "2026-07-14T20:51:11.672662Z",
      "duration_seconds": 156.56,
      "target_new_cards": 5,
      "rounds": 1,
      "pool_before": 319,
      "pool_after": 295,
      "processed": 24,
      "proposals": 17,
      "reviewed": 17,
      "added": 5,
      "pass_rate": 20.8,
      "input_tokens": 18436,
      "output_tokens": 8342,
      "filters": {
        "before_ai": {
          "invalid_record": 0,
          "duplicate_source": 0,
          "seen_recently": 0,
          "low_information": 0,
          "explicit_topic_selected": 24,
          "random_selected": 0,
          "average_hook_score": 7
        },
        "before_review": {
          "low_confidence": 0,
          "missing_candidate": 0,
          "bad_title": 0,
          "bad_category": 0,
          "similar_title": 0,
          "semantic_duplicate": 0
        },
        "final": {
          "model_rejected": 0,
          "score_below_78": 0,
          "bad_title": 0,
          "bad_category": 0,
          "evidence_mismatch": 0,
          "duplicate_source": 0,
          "similar_title": 0,
          "semantic_duplicate": 0
        }
      },
      "source_stats": {
        "维基主题分类": {
          "processed": 24,
          "accepted": 5
        }
      },
      "quality": {
        "category_distribution": {
          "科学": 15,
          "历史": 7,
          "科技": 7,
          "生物": 6,
          "生活": 5,
          "艺术": 3,
          "综合": 1
        },
        "new_category_distribution": {
          "科学": 2,
          "科技": 2,
          "历史": 1
        },
        "source_pass_rates": {
          "维基主题分类": {
            "processed": 24,
            "accepted": 5,
            "pass_rate": 20.8
          }
        },
        "review_pass_rate": 29.4,
        "processed_pass_rate": 20.8,
        "evidence_mismatch": 0,
        "evidence_mismatch_rate": 0.0
      }
    },
    {
      "github_run_id": "29283727614",
      "source": "workflow_run",
      "started_at": "2026-07-13T20:46:39.460407Z",
      "finished_at": "2026-07-13T20:50:53.922944Z",
      "duration_seconds": 254.46,
      "target_new_cards": 5,
      "rounds": 1,
      "pool_before": 291,
      "pool_after": 267,
      "processed": 24,
      "proposals": 17,
      "reviewed": 17,
      "added": 5,
      "pass_rate": 20.8,
      "input_tokens": 41784,
      "output_tokens": 8920,
      "filters": {
        "before_ai": {
          "invalid_record": 0,
          "duplicate_source": 0,
          "seen_recently": 0,
          "low_information": 0,
          "explicit_topic_selected": 24,
          "random_selected": 0,
          "average_hook_score": 8
        },
        "before_review": {
          "low_confidence": 0,
          "missing_candidate": 0,
          "bad_title": 0,
          "bad_category": 0,
          "similar_title": 0,
          "semantic_duplicate": 0
        },
        "final": {
          "model_rejected": 0,
          "score_below_78": 0,
          "bad_title": 0,
          "bad_category": 0,
          "evidence_mismatch": 1,
          "duplicate_source": 0,
          "similar_title": 0,
          "semantic_duplicate": 0
        }
      },
      "source_stats": {
        "维基主题分类": {
          "processed": 24,
          "accepted": 5
        }
      },
      "quality": {
        "category_distribution": {
          "科学": 13,
          "历史": 6,
          "生物": 6,
          "生活": 5,
          "科技": 5,
          "艺术": 3,
          "综合": 1
        },
        "new_category_distribution": {
          "历史": 1,
          "生活": 1,
          "生物": 1,
          "科学": 1,
          "科技": 1
        },
        "source_pass_rates": {
          "维基主题分类": {
            "processed": 24,
            "accepted": 5,
            "pass_rate": 20.8
          }
        },
        "review_pass_rate": 29.4,
        "processed_pass_rate": 20.8,
        "evidence_mismatch": 1,
        "evidence_mismatch_rate": 5.9
      }
    },
    {
      "github_run_id": "29265190384",
      "source": "web",
      "started_at": "2026-07-13T16:08:52.333045Z",
      "finished_at": "2026-07-13T16:10:51.772689Z",
      "duration_seconds": 119.44,
      "target_new_cards": 5,
      "rounds": 1,
      "pool_before": 239,
      "pool_after": 215,
      "processed": 24,
      "proposals": 16,
      "reviewed": 8,
      "added": 5,
      "pass_rate": 20.8,
      "input_tokens": 31115,
      "output_tokens": 5927,
      "filters": {
        "before_ai": {
          "invalid_record": 0,
          "duplicate_source": 0,
          "seen_recently": 0,
          "low_information": 0,
          "explicit_topic_selected": 24,
          "random_selected": 0,
          "average_hook_score": 8
        },
        "before_review": {
          "low_confidence": 8,
          "missing_candidate": 0,
          "bad_title": 0,
          "bad_category": 0,
          "similar_title": 0,
          "semantic_duplicate": 0
        },
        "final": {
          "model_rejected": 0,
          "score_below_78": 0,
          "bad_title": 0,
          "bad_category": 0,
          "evidence_mismatch": 0,
          "duplicate_source": 0,
          "similar_title": 0,
          "semantic_duplicate": 0
        }
      },
      "source_stats": {
        "维基主题分类": {
          "processed": 21,
          "accepted": 4
        },
        "NASA APOD": {
          "processed": 3,
          "accepted": 1
        }
      },
      "quality": {
        "category_distribution": {
          "科学": 12,
          "历史": 5,
          "生物": 5,
          "生活": 4,
          "科技": 4,
          "艺术": 3,
          "综合": 1
        },
        "new_category_distribution": {
          "科学": 2,
          "历史": 1,
          "生活": 1,
          "综合": 1
        },
        "source_pass_rates": {
          "维基主题分类": {
            "processed": 21,
            "accepted": 4,
            "pass_rate": 19.0
          },
          "NASA APOD": {
            "processed": 3,
            "accepted": 1,
            "pass_rate": 33.3
          }
        },
        "review_pass_rate": 62.5,
        "processed_pass_rate": 20.8,
        "evidence_mismatch": 0,
        "evidence_mismatch_rate": 0.0
      }
    },
    {
      "github_run_id": "29188943454",
      "source": "web",
      "started_at": "2026-07-12T10:24:03.216364Z",
      "finished_at": "2026-07-12T10:24:36.478086Z",
      "duration_seconds": 33.26,
      "target_new_cards": 12,
      "rounds": 1,
      "harvested": 3,
      "new_candidates": 3,
      "pool_before": 0,
      "pool_after": 0,
      "processed": 3,
      "proposals": 2,
      "reviewed": 2,
      "added": 0,
      "pass_rate": 0.0,
      "input_tokens": 11859,
      "output_tokens": 1311,
      "filters": {
        "harvest": {
          "already_in_pool": 0,
          "already_published": 0,
          "seen_recently": 0,
          "low_information": 0,
          "pool_limit": 0
        },
        "before_ai": {
          "invalid_record": 0,
          "duplicate_source": 0,
          "seen_recently": 0,
          "low_information": 0
        },
        "before_review": {
          "low_confidence": 0,
          "missing_candidate": 0,
          "bad_title": 0,
          "bad_category": 0,
          "similar_title": 0
        },
        "final": {
          "model_rejected": 0,
          "score_below_78": 0,
          "bad_title": 0,
          "bad_category": 0,
          "evidence_mismatch": 2,
          "duplicate_source": 0,
          "similar_title": 0
        }
      },
      "source_stats": {
        "大都会博物馆": {
          "processed": 3,
          "accepted": 0
        }
      }
    },
    {
      "github_run_id": "29188666985",
      "source": "web",
      "started_at": "2026-07-12T10:12:56.013894Z",
      "finished_at": "2026-07-12T10:14:15.846876Z",
      "duration_seconds": 79.83,
      "target_new_cards": 12,
      "rounds": 1,
      "harvested": 11,
      "new_candidates": 11,
      "pool_before": 0,
      "pool_after": 0,
      "processed": 11,
      "proposals": 7,
      "reviewed": 7,
      "added": 6,
      "pass_rate": 54.5,
      "input_tokens": 21625,
      "output_tokens": 3450,
      "filters": {
        "harvest": {
          "already_in_pool": 0,
          "already_published": 0,
          "seen_recently": 0,
          "low_information": 0,
          "pool_limit": 0
        },
        "before_ai": {
          "invalid_record": 0,
          "duplicate_source": 0,
          "seen_recently": 0,
          "low_information": 0
        },
        "before_review": {
          "low_confidence": 0,
          "missing_candidate": 0,
          "bad_title": 0,
          "bad_category": 0,
          "similar_title": 0
        },
        "final": {
          "model_rejected": 0,
          "score_below_78": 0,
          "bad_title": 0,
          "bad_category": 0,
          "evidence_mismatch": 1,
          "duplicate_source": 0,
          "similar_title": 0
        }
      },
      "source_stats": {
        "大都会博物馆": {
          "processed": 3,
          "accepted": 0
        },
        "英文维基分类": {
          "processed": 8,
          "accepted": 6
        }
      }
    }
  ],
  "last_harvest": {
    "github_run_id": "29441144903",
    "source": "harvest_schedule",
    "started_at": "2026-07-15T18:35:23.915831Z",
    "finished_at": "2026-07-15T18:41:22.244768Z",
    "passes": 4,
    "fetched": 649,
    "added": 48,
    "pool_before": 295,
    "pool_after": 343,
    "target_pool_size": 500,
    "refill_trigger": 300,
    "refill_needed": true,
    "source_counts": {
      "维基主题分类": 142,
      "历史上的今天": 2,
      "英文维基随机": 400,
      "中文维基随机": 105
    },
    "success": true,
    "min_added_for_success": 20,
    "ok_sources": [
      "Wikipedia topic samples",
      "Wikimedia On This Day",
      "English Wikipedia random pass 1",
      "Chinese Wikipedia random pass 1",
      "English Wikipedia random pass 2",
      "Chinese Wikipedia random pass 2",
      "English Wikipedia random pass 3",
      "Chinese Wikipedia random pass 3",
      "English Wikipedia random pass 4",
      "Chinese Wikipedia random pass 4"
    ],
    "diagnostic_report": "data/harvest_report.json",
    "message": "候选囤货成功"
  }
}
